brickstudy/__init__.py
brickstudy/foundation.py
brickstudy-0.0.1.dist-info/LICENSE.md
brickstudy-0.0.1.dist-info/METADATA
brickstudy-0.0.1.dist-info/WHEEL
brickstudy-0.0.1.dist-info/top_level.txt
brickstudy-0.0.1.dist-info/RECORD
