Metadata-Version: 2.1
Name: brickstudy
Version: 0.0.1
Summary: A package for analysis of MRI
Home-page: https://github.com/brickstudymasons/brickstudy
Author: BRICK team at Rotterdam University Medical Center
Author-email: c.moore@esciencecenter.nl
License: Apache 2.0
License-File: LICENSE.md
Requires-Dist: numpy <2.0.0
Requires-Dist: pyxdf
Requires-Dist: pandas
Requires-Dist: openpyxl
Requires-Dist: scipy
Requires-Dist: matplotlib
Requires-Dist: scikit-learn
Requires-Dist: SimpleITK
Requires-Dist: seaborn
Requires-Dist: nibabel
Requires-Dist: ipywidgets
Requires-Dist: imageio <=2.31.5
Requires-Dist: scikit-image
Provides-Extra: dev
Requires-Dist: pytest ; extra == 'dev'
Requires-Dist: codestyle ; extra == 'dev'
Requires-Dist: isort ; extra == 'dev'
Requires-Dist: wheel ; extra == 'dev'
Requires-Dist: jupyter ; extra == 'dev'
Requires-Dist: ipympl ; extra == 'dev'
